phyca/CUS.tsv
phyca/__init__.py
phyca/phyca.py
phyca-0.0.2.dist-info/LICENSE
phyca-0.0.2.dist-info/METADATA
phyca-0.0.2.dist-info/WHEEL
phyca-0.0.2.dist-info/entry_points.txt
phyca-0.0.2.dist-info/top_level.txt
phyca-0.0.2.dist-info/RECORD
