Metadata-Version: 2.1
Name: phyca
Version: 0.0.2
Summary: Universal ortholog based Phylogenomic toolkit.
Home-page: https://github.com/DeadlineWasYesterday/phyca
Author: Md Nafis Ul Alam
Author-email: deadlinewasyesterday@gmail.com
Classifier: Intended Audience :: Developers
Classifier: Intended Audience :: Science/Research
Classifier: License :: Freely Distributable
Classifier: Operating System :: OS Independent
Classifier: Programming Language :: Python
Classifier: Programming Language :: Python :: 3.12
Classifier: Topic :: Scientific/Engineering
Classifier: Topic :: Scientific/Engineering :: Bio-Informatics
Requires-Python: >=3.8
License-File: LICENSE
Requires-Dist: numpy
Requires-Dist: pandas>=2
Requires-Dist: matplotlib
Requires-Dist: seaborn
Requires-Dist: biopython
Requires-Dist: BioNick
Requires-Dist: scipy
